sksurgeryarucotracker/__init__.py
sksurgeryarucotracker/__main__.py
sksurgeryarucotracker/_version.py
sksurgeryarucotracker/arucotracker.py
scikit_surgeryarucotracker-0.0.4.dist-info/LICENSE
scikit_surgeryarucotracker-0.0.4.dist-info/METADATA
scikit_surgeryarucotracker-0.0.4.dist-info/WHEEL
scikit_surgeryarucotracker-0.0.4.dist-info/entry_points.txt
scikit_surgeryarucotracker-0.0.4.dist-info/top_level.txt
scikit_surgeryarucotracker-0.0.4.dist-info/RECORD
